README.rst
setup.cfg
setup.py
src/powerbi_publisher/__init__.py
src/powerbi_publisher/cli.py
src/powerbi_publisher/powerbi.py
src/powerbi_publisher.egg-info/PKG-INFO
src/powerbi_publisher.egg-info/SOURCES.txt
src/powerbi_publisher.egg-info/dependency_links.txt
src/powerbi_publisher.egg-info/entry_points.txt
src/powerbi_publisher.egg-info/not-zip-safe
src/powerbi_publisher.egg-info/requires.txt
src/powerbi_publisher.egg-info/top_level.txt
src/powerbi_publisher/test/__init__.py
src/powerbi_publisher/test/conftest.py
src/powerbi_publisher/test/test_powerbi.py