Metadata-Version: 1.1
Name: powerbi-publisher
Version: 0.2.1
Summary: A tool to easily publish Power BI reports on Power BI Web through a command line interface (CLI).
Home-page: https://www.optelgroup.com
Author: Optel Group
Author-email: btechsupport@optelgroup.com
License: Private
Download-URL: https://vcs.optelgroup.com/btech/bi/data-refinery/powerbi-publisher/repository/master/archive.tar.gz
Project-URL: Documentation, http://btechdoc.optelgroup.com
Project-URL: Source Code, https://vcs.optelgroup.com/btech/bi/data-refinery/powerbi-publisher
Project-URL: Bug Tracker, https://vcs.optelgroup.com/btech/bi/data-refinery/powerbi-publisher/issues
Platform: UNKNOWN
Classifier: Intended Audience :: Developers
Classifier: Operating System :: OS Independent
Classifier: Programming Language :: Python
